README.md
setup.cfg
setup.py
ml_basicss/__init__.py
ml_basicss.egg-info/PKG-INFO
ml_basicss.egg-info/SOURCES.txt
ml_basicss.egg-info/dependency_links.txt
ml_basicss.egg-info/not-zip-safe
ml_basicss.egg-info/top_level.txt