Metadata-Version: 1.0
Name: ml-basicss
Version: 0.1
Summary: first test
Home-page: https://github.com/kaushal793/ml_basics
Author: Kaushal Paneri
Author-email: paneri.k@husky.neu.edu
License: MIT
Platform: UNKNOWN
